{
  "lang": "Japanese",
  "sentenceDatasetName": "hiragana_sy",
  "sentenceDatasetScreenName": "ひらがな しゃ・じゃ行",
  "words": [
    {
      "wordSection": "__BASE__",
      "sentence": "しゃ",
      "typeString": "しゃ"
    },
    {
      "wordSection": "__BASE__",
      "sentence": "しぃ",
      "typeString": "しぃ"
    },
    {
      "wordSection": "__BASE__",
      "sentence": "しゅ",
      "typeString": "しゅ"
    },
    {
      "wordSection": "__BASE__",
      "sentence": "しぇ",
      "typeString": "しぇ"
    },
    {
      "wordSection": "__BASE__",
      "sentence": "しょ",
      "typeString": "しょ"
    },
    {
      "wordSection": "__BASE__",
      "sentence": "じゃ",
      "typeString": "じゃ"
    },
    {
      "wordSection": "__BASE__",
      "sentence": "じぃ",
      "typeString": "じぃ"
    },
    {
      "wordSection": "__BASE__",
      "sentence": "じゅ",
      "typeString": "じゅ"
    },
    {
      "wordSection": "__BASE__",
      "sentence": "じぇ",
      "typeString": "じぇ"
    },
    {
      "wordSection": "__BASE__",
      "sentence": "じょ",
      "typeString": "じょ"
    }
  ]
}
