{
  "lang": "Japanese",
  "sentenceDatasetName": "keyboardMiddle",
  "sentenceDatasetScreenName": "キーボード中段",
  "words": [
    {
      "wordSection": 0,
      "sentence": "a(エー)",
      "typeString": "a"
    },
    {
      "wordSection": 0,
      "sentence": "s(エス)",
      "typeString": "s"
    },
    {
      "wordSection": 0,
      "sentence": "d(ディー)",
      "typeString": "d"
    },
    {
      "wordSection": 0,
      "sentence": "f(エフ)",
      "typeString": "f"
    },
    {
      "wordSection": 0,
      "sentence": "g(ジー)",
      "typeString": "g"
    },
    {
      "wordSection": 0,
      "sentence": "h(エイチ)",
      "typeString": "h"
    },
    {
      "wordSection": 0,
      "sentence": "j(ジェー)",
      "typeString": "j"
    },
    {
      "wordSection": 0,
      "sentence": "k(ケー)",
      "typeString": "k"
    },
    {
      "wordSection": 0,
      "sentence": "l(エル)",
      "typeString": "l"
    },
    {
      "wordSection": 0,
      "sentence": ";(セミコロン)",
      "typeString": ";"
    },
    {
      "wordSection": 0,
      "sentence": ":(コロン)",
      "typeString": ":"
    }
  ]
}
